my_js_parser/__init__.py
my_js_parser/parser.py
my_js_parser-0.9.dist-info/METADATA
my_js_parser-0.9.dist-info/WHEEL
my_js_parser-0.9.dist-info/top_level.txt
my_js_parser-0.9.dist-info/RECORD
