Metadata-Version: 2.1
Name: my_js_parser
Version: 0.9
Requires-Dist: lxml
Requires-Dist: quickjs
